LICENSE.txt
README.md
setup.py
counterplots/__init__.py
counterplots.egg-info/PKG-INFO
counterplots.egg-info/SOURCES.txt
counterplots.egg-info/dependency_links.txt
counterplots.egg-info/requires.txt
counterplots.egg-info/top_level.txt
counterplots/utils/__init__.py
counterplots/utils/plots.py
counterplots/utils/process.py
counterplots/utils/verification.py
tests/__init__.py
tests/test____init__.py
tests/utils/__init__.py
tests/utils/test_plots.py
tests/utils/test_process.py
tests/utils/test_verification.py