Metadata-Version: 2.1
Name: counterplots
Version: 0.0.5
Summary: Plotting tool for counterfactual explanations
Home-page: https://github.com/ADMAntwerp/CounterPlots
Download-URL: https://pypi.org/project/counterplots/
Author: Raphael Mazzine Barbosa de Oliveira, Bjorge Meulemeester
License: MIT
Keywords: Counterfactual Explanations,Visualization,Plotting,Explainable Artificial Intelligence,XAI,Machine Learning
License-File: LICENSE.txt
